datasette_sqlite_authorizer/__init__.py
datasette_sqlite_authorizer-0.2.dist-info/LICENSE
datasette_sqlite_authorizer-0.2.dist-info/METADATA
datasette_sqlite_authorizer-0.2.dist-info/WHEEL
datasette_sqlite_authorizer-0.2.dist-info/entry_points.txt
datasette_sqlite_authorizer-0.2.dist-info/top_level.txt
datasette_sqlite_authorizer-0.2.dist-info/RECORD
