Metadata-Version: 2.1
Name: datasette-sqlite-authorizer
Version: 0.2
Summary: Configure Datasette to block operations using the SQLite set_authorizer mechanism
Author: Simon Willison
License: Apache-2.0
Project-URL: Homepage, https://github.com/simonw/datasette-sqlite-authorizer
Project-URL: Changelog, https://github.com/simonw/datasette-sqlite-authorizer/releases
Project-URL: Issues, https://github.com/simonw/datasette-sqlite-authorizer/issues
Project-URL: CI, https://github.com/simonw/datasette-sqlite-authorizer/actions
Classifier: Framework :: Datasette
Classifier: License :: OSI Approved :: Apache Software License
Requires-Python: >=3.8
License-File: LICENSE
Requires-Dist: datasette
Provides-Extra: test
Requires-Dist: pytest ; extra == 'test'
Requires-Dist: pytest-asyncio ; extra == 'test'
Requires-Dist: datasette-test ; extra == 'test'
